dydx/__init__.py
dydx/client.py
dydx/constants.py
dydx/eth.py
dydx/eth_perp.py
dydx/eth_solo.py
dydx/exceptions.py
dydx/perp_orders.py
dydx/solo_orders.py
dydx/util.py
dydx/abi/erc20.json
dydx/abi/payableproxy.json
dydx/abi/perpetualv1.json
dydx/abi/solomargin.json
dydx/abi/wethproxy.json
tests/__init__.py
tests/test_client.py
tests/test_eth.py
tests/test_json.py
tests/test_perp_orders.py
tests/test_solo_orders.py
tests/test_util.py
dydx_python-0.11.3.dist-info/LICENSE
dydx_python-0.11.3.dist-info/METADATA
dydx_python-0.11.3.dist-info/WHEEL
dydx_python-0.11.3.dist-info/top_level.txt
dydx_python-0.11.3.dist-info/RECORD
